foundationallm/__init__.py
foundationallm/_version.py
foundationallm/_metadata/foundationallm_manifest.json
foundationallm/config/__init__.py
foundationallm/config/configuration.py
foundationallm/config/context.py
foundationallm/config/environment_variables.py
foundationallm/config/user_identity.py
foundationallm/event_handlers/__init__.py
foundationallm/event_handlers/openai_assistant_async_event_handler.py
foundationallm/exceptions/__init__.py
foundationallm/exceptions/foundationallm_exception.py
foundationallm/langchain/__init__.py
foundationallm/langchain/agents/__init__.py
foundationallm/langchain/agents/agent_base.py
foundationallm/langchain/agents/agent_factory.py
foundationallm/langchain/agents/generic_agent.py
foundationallm/langchain/common/__init__.py
foundationallm/langchain/common/foundationallm_tool_base.py
foundationallm/langchain/common/foundationallm_tool_result.py
foundationallm/langchain/common/foundationallm_workflow_base.py
foundationallm/langchain/exceptions/__init__.py
foundationallm/langchain/exceptions/langchain_exception.py
foundationallm/langchain/language_models/__init__.py
foundationallm/langchain/language_models/language_model_factory.py
foundationallm/langchain/orchestration/__init__.py
foundationallm/langchain/orchestration/orchestration_manager.py
foundationallm/langchain/retrievers/__init__.py
foundationallm/langchain/retrievers/agent_parameter_retriever_keys.py
foundationallm/langchain/retrievers/azure_ai_search_service_retriever.py
foundationallm/langchain/retrievers/content_artifact_retrieval_base.py
foundationallm/langchain/retrievers/multi_index_retriever.py
foundationallm/langchain/retrievers/retriever_factory.py
foundationallm/langchain/retrievers/search_service_filter_retriever.py
foundationallm/langchain/toolkits/__init__.py
foundationallm/langchain/toolkits/anomaly_detection_toolkit.py
foundationallm/langchain/toolkits/secure_sql_database_toolkit.py
foundationallm/langchain/tools/__init__.py
foundationallm-0.9.7.post10.dist-info/licenses/LICENSE
foundationallm-0.9.7.post10.dist-info/METADATA
foundationallm-0.9.7.post10.dist-info/WHEEL
foundationallm-0.9.7.post10.dist-info/top_level.txt
foundationallm-0.9.7.post10.dist-info/RECORD
