Metadata-Version: 2.4
Name: foundationallm
Version: 0.9.7.post10
Summary: Enables integration with the FoundationaLLM platform.
Author-email: FoundationaLLM <dev@foundationallm.ai>
License-Expression: MIT
Project-URL: Homepage, https://foundationallm.ai
Project-URL: Issues, https://github.com/foundationallm/foundationallm/issues
Classifier: Programming Language :: Python :: 3
Classifier: Operating System :: OS Independent
Requires-Python: >=3.11
License-File: LICENSE
Dynamic: license-file
